migo.py
migo-0.0.6.dist-info/entry_points.txt
migo-0.0.6.dist-info/LICENSE
migo-0.0.6.dist-info/WHEEL
migo-0.0.6.dist-info/METADATA
migo-0.0.6.dist-info/RECORD
